LICENSE
README.md
setup.cfg
setup.py
lib/djWasabi/__init__.py
lib/djWasabi/config.py
lib/djWasabi/container.py
lib/djWasabi/generic.py
lib/djWasabi/git.py
lib/djWasabi/http.py
lib/dj_wasabi.egg-info/PKG-INFO
lib/dj_wasabi.egg-info/SOURCES.txt
lib/dj_wasabi.egg-info/dependency_links.txt
lib/dj_wasabi.egg-info/requires.txt
lib/dj_wasabi.egg-info/top_level.txt
tests/test_config.py
tests/test_container.py
tests/test_generic.py
tests/test_git.py
tests/test_http.py